formable/__init__.py
formable/_version.py
formable/levenberg_marquardt.py
formable/load_cases.py
formable/load_response.py
formable/maths_utils.py
formable/tensile_test.py
formable/utils.py
formable/yielding/__init__.py
formable/yielding/base.py
formable/yielding/map.py
formable/yielding/simulation.py
formable/yielding/yield_functions.py
formable/yielding/yield_point.py
formable-0.1.21.dist-info/LICENSE
formable-0.1.21.dist-info/METADATA
formable-0.1.21.dist-info/WHEEL
formable-0.1.21.dist-info/top_level.txt
formable-0.1.21.dist-info/RECORD
